[
    {
      "name": "Tech Innovations Inc.",
      "address": "123 Main St, Anytown, AN 12345",
      "phone": "+1 (555) 123-4567",
      "website": "https://techinnovations.example.com",
      "image": "placeholder.png",
      "membershipLevel": 3,
      "description": "Leading provider of AI-driven business solutions."
    },
    {
      "name": "Green Earth Farms",
      "address": "456 Oak Ave, Somewhere, SW 67890",
      "phone": "+1 (555) 987-6543",
      "website": "https://greenearthfarms.example.com",
      "image": "placeholder.png",
      "membershipLevel": 2,
      "description": "Organic produce and sustainable farming."
    },
    {
      "name": "Summit Builders",
      "address": "789 Pine Rd, Highlands, HL 34567",
      "phone": "+1 (555) 456-7890",
      "website": "https://summitbuilders.example.com",
      "image": "placeholder.png",
      "membershipLevel": 1,
      "description": "Commercial and residential construction experts."
    },
    {
      "name": "Blue Ocean Logistics",
      "address": "321 Harbor Blvd, Portville, PV 87654",
      "phone": "+1 (555) 234-5678",
      "website": "https://blueocean.example.com",
      "image": "placeholder.png",
      "membershipLevel": 3,
      "description": "Global shipping and supply chain management."
    },
    {
      "name": "Pioneer Marketing",
      "address": "654 Market St, Downtown, DT 54321",
      "phone": "+1 (555) 345-6789",
      "website": "https://pioneermarketing.example.com",
      "image": "placeholder.png",
      "membershipLevel": 2,
      "description": "Data-driven digital marketing agency."
    },
    {
      "name": "Sunrise Café",
      "address": "987 Sunrise Ln, Riverside, RS 13579",
      "phone": "+1 (555) 567-8901",
      "website": "https://sunrisecafe.example.com",
      "image": "placeholder.png",
      "membershipLevel": 1,
      "description": "Artisanal coffee and baked goods."
    },
    {
      "name": "Elite Fitness",
      "address": "246 Gym Way, Healthville, HV 86420",
      "phone": "+1 (555) 678-9012",
      "website": "https://elitefitness.example.com",
      "image": "placeholder.png",
      "membershipLevel": 3,
      "description": "Premium gym with personalized training programs."
    }
  ]